<?xml version="1" encoding="UTF-8" standalone="yes"?>

<!--<WasabiXML version="1.2">-->
<WasabiXML version="1.34">

<skininfo>
<version>1</version>
<name>BUG AMP</name>
<comment>Skin full of bugs</comment>
<author gaybag="pjn123">Pieter</author>
<email></email>
<homepage></homepage>
<screenshot></screenshot>
</skininfo>

<include file="player-elements.xml"/>
<include file="CentroTab.xml"/>
<container id="main" name="Main Window">

<groupdef id="allstuff">
<Cpro:Tab id="haha1" x="0" y="0" tabtext="Library"/>

	<script file="CproTab.maki"/>

</groupdef>



<layout id="normal" minimum_w="602" minimum_h="337" maximum_w="800" maximum_h="600" rectrgn="1">
  <wasabi:StandardFrame:Status fitparent="1" content="allstuff" wantfocus="1" />
  <sendparams target="window.titlebar.title" default="List color bug (Winamp5 build 2225)"/>
</layout>
</container>



</WasabiXML>