	<!--<include file="player-shade-group.xml"/>-->

<groupdef id="shade.seeker.active">
	<grid id="shade.seeker.active.layer" x="0" y="0" w="550" h="40" topleft="shade.seeker.1.1" top="shade.seeker.1.2" topright="shade.seeker.1.3" alpha="253"/>
	<grid id="shade.seeker.hover.layer" x="0" y="0" w="550" h="40" topleft="shade.seeker.2.1" top="shade.seeker.2.2" topright="shade.seeker.2.3" alpha="0"/>
	<layer id="shade.seeker.active.light" x="0" y="0" visible="0" image="info.bg.seeker.light" alpha="253"/>
</groupdef>
<groupdef id="shade.seeker.finder">
	<grid id="shade.seeker.finder.layer" x="0" y="0" w="550" h="40" topleft="shade.seeker.3.1" top="shade.seeker.3.2" topright="shade.seeker.3.3" alpha="253"/>
</groupdef>


<groupdef id="shade.sect.stop">
	<layer x="0" y="0" image="shade.bg.4" wantfocus="1" ghost="1"/>
	<button id="shade.stop" x="0" y="0" action="STOP" image="s.stop.1" downimage="s.stop.3"/>
	<layer id="shade.stop.fade" x="0" y="0" image="s.stop.2" ghost="1" alpha="0"/>
	<script file="@WINAMPPATH@\Plugins\classicPro\engine\two\scripts\buttonfade.maki" param="shade.stop;shade.stop.fade"/>
</groupdef>

<groupdef id="shade.sect.shuf">
	<layer x="0" y="0" image="shade.bg.5" wantfocus="1" ghost="1"/>
	<NStatesButton id="shade.shuf" x="0" y="0" image="s.shuf.1." hoverimage="s.shuf.2." downimage="s.shuf.3." rectrgn="1" nstates="2" tooltip="Toggle Playlist Shuffling" cfgattrib="{45F3F7C1-A6F3-4EE6-A15E-125E92FC3F8D};Shuffle"/>
	<layer id="shade.shuf.fade" x="0" y="0" ghost="1" alpha="0"/>
	<script file="@WINAMPPATH@\Plugins\classicPro\engine\two\scripts\buttonfade.maki" param="shade.shuf;shade.shuf.fade;s.shuf.2."/>
</groupdef>
<groupdef id="shade.sect.rep">
	<layer x="0" y="0" image="shade.bg.6" wantfocus="1" ghost="1"/>
	<NStatesButton id="shade.rep" x="0" y="0" image="s.rep.1." hoverimage="s.rep.2." downimage="s.3." rectrgn="1" nstates="3" tooltip="Toggle Playlist/Song Repeating" cfgattrib="{45F3F7C1-A6F3-4EE6-A15E-125E92FC3F8D};Repeat" cfgvals="0;1;-1"/>
	<layer id="shade.rep.fade" x="0" y="0" ghost="1" alpha="0"/>
	<script file="@WINAMPPATH@\Plugins\classicPro\engine\two\scripts\buttonfade.maki" param="shade.rep;shade.rep.fade;s.rep.2."/>
</groupdef>

<groupdef id="shade.sect.seek">
	<grid fitparent="1" topleft="shade.bg.7" top="shade.bg.8" topright="shade.bg.9" wantfocus="1" ghost="1"/>

	<group id="shade.seeker.active" x="0" y="0" w="0" h="40"/>
	<group id="shade.seeker.finder" x="0" y="0" w="0" h="40" alpha="175"/> <!-- Remove alpha l@r... image can do it-->

	<slider id="shade.seeker.slider.0" x="0" y="0" w="0" h="0" relatw="1" relath="1" action="SEEK" thumb="info.seeker.thumb" interval="50"/>
	<slider id="shade.seeker.slider.1" x="0" y="0" w="0" h="0" relatw="1" relath="1" action="SEEK" thumb="info.seeker.thumb" cursor="IDC_HAND"/>
	<ModernSongticker id="Songticker"
		fitparent="1" y="5" antialias="1"
		id_layout="main;shade"
		id_volume="Volume"
		id_seeker="seeker"
		id_prev="previous.track"
		id_next="next.track"
		id_open="open.tracks"
		id_shuf="shuffle"
		id_rep="repeat"
		id_mute="mute2"
		fontsize="12"
		font="cpro.winshade.font"
		color="0,0,0"
		align="center" ghost_all="1"
	/>
	
	
	<script file="@WINAMPPATH@\Plugins\classicPro\engine\two\scripts\shade-seeker.maki"/>
</groupdef>
<groupdef id="shade.sect.vis">
	<layer regionop="1" image="shade.bg.10" wantfocus="1" ghost="1"/>
</groupdef>



<layout id="shade" minimum_h="22" minimum_w="240" maximum_h="22" h="22" w="240" appbar="top|bottom" wantfocus="1" linkwidth="normal">
	<group id="cpro.shade.background" fitparent="1" sysregion="1"/>

	<layer fitparent="1" dblClickAction="SWITCH;normal"/>
	
	<layer x="0" y="0" regionop="1" image="shade.bg.1" wantfocus="1" ghost="1"/>
	<layer x="90" y="0" w="-173" relatw="1" regionop="1" image="shade.bg.2" wantfocus="1" ghost="1"/>
	<layer x="-83" y="0" relatx="1" regionop="1" image="shade.bg.11" wantfocus="1" ghost="1"/>

	<layer x="90" y="0" image="shade.bg.3" wantfocus="1" ghost="1"/>


	<button id="shade.prev" x="90" y="0" action="PREV" image="s.prev.1" downimage="s.prev.3"/>
	<layer id="shade.prev.fade" x="90" y="0" image="s.prev.2" ghost="1" alpha="0"/>
	<script file="@WINAMPPATH@\Plugins\classicPro\engine\two\scripts\buttonfade.maki" param="shade.prev;shade.prev.fade"/>

	<button id="shade.play" x="110" y="0" action="PLAY" image="s.play.1" downimage="s.play.3"/>
	<layer id="shade.play.fade" x="110" y="0" image="s.play.2" ghost="1" alpha="0"/>
	<script file="@WINAMPPATH@\Plugins\classicPro\engine\two\scripts\buttonfade.maki" param="shade.play;shade.play.fade"/>

	<button id="shade.next" x="130" y="0" action="NEXT" image="s.next.1" downimage="s.next.3"/>
	<layer id="shade.next.fade" x="130" y="0" image="s.next.2" ghost="1" alpha="0"/>
	<script file="@WINAMPPATH@\Plugins\classicPro\engine\two\scripts\buttonfade.maki" param="shade.next;shade.next.fade"/>




	<group id="shade.sect.stop" x="150" y="0" w="20" h="22"/>
	<group id="shade.sect.shuf" x="170" y="0" w="20" h="22"/>
	<group id="shade.sect.rep" x="190" y="0" w="20" h="22"/>
	<group id="shade.sect.seek" x="212" y="0" w="-388" h="22" relatw="1"/> <!-- short 297-->
	<group id="shade.sect.vis" x="-178" y="0" w="95" h="22" relatx="1"/>

	<script file="@WINAMPPATH@\Plugins\classicPro\engine\two\scripts\shade.maki"/>
	
	
	
	<layer id="resizer.6" x="-8" y="0" w="8" h="22" relatx="1" cursor="IDC_SIZEWE" move="0"/>
	<script file="@WINAMPPATH@\Plugins\classicPro\engine\two\scripts\shade-resizer.maki"/>


	<!--<group id="cpro.shade.underlay" fitparent="1" sysregion="1"/>


	<layer x="0" y="0" image="shade.o.bg.1" wantfocus="1" ghost="1"/>
	<layer x="90" y="0" w="-280" relatw="1" image="shade.o.bg.2" wantfocus="1" ghost="1"/>
	<layer x="-191" y="0" relatx="1" image="shade.o.bg.3" wantfocus="1" ghost="1"/>
	
	


	<button id="shade.mlmenu.visible" x="6" y="3" image="s.menu.1" hoverImage="s.menu.2" downImage="s.menu.3" rectrgn="1" tooltip="Library's Playlists"/>
	<button id="shade.mlmenu.fake" x="6" y="20" w="1" h="1" visible="0" action="PE_ListOfLists"/>

	<Button id="previous.track"
		x="-186" y="4" relatx="1"
		image="s.prev.1"
		hoverImage="s.prev.2"
		downImage="s.prev.3"
		rectrgn="1" action="PREV" tooltip="Previous Track"
	/>

	<Button id="Play"
		x="-173" y="4" relatx="1"
		image="s.play.1"
		hoverImage="s.play.2"
		downImage="s.play.3"
		rectrgn="1" action="PLAY" tooltip="Play"
	/>

	<Button id="Pause"
		x="-160" y="4" relatx="1"
		image="s.pause.1"
		hoverImage="s.pause.2"
		downImage="s.pause.3"
		rectrgn="1" action="PAUSE" tooltip="Pause Playback"
	/>

	<Button id="Stop"
		x="-147" y="4" relatx="1"
		image="s.stop.1"
		hoverImage="s.stop.2"
		downImage="s.stop.3"
		rectrgn="1" action="STOP" tooltip="Stop Playback"
	/>

	<Button id="next.track"
		x="-134" y="4" relatx="1"
		image="s.next.1"
		hoverImage="s.next.2"
		downImage="s.next.3"
		rectrgn="1" action="NEXT" tooltip="Next Track"
	/>

	<Button id="open.tracks"
		x="-114" y="4" relatx="1"
		image="s.eject.1"
		hoverImage="s.eject.2"
		downImage="s.eject.3"
		rectrgn="1" action="EJECT" tooltip="Open File(s)"
	/>
	<script file="@WINAMPPATH@\Plugins\classicPro\engine\one\scripts\extendedbuttons.maki"/>

	<group id="shade.visgroup" x="91" y="0" w="63" h="23" move="1" visible="0"/>
	<group id="shade.volgroup" x="154" y="0" w="69" h="23" move="1" visible="0"/>
	<group id="shade.seekticker" x="223" y="0" w="-414" h="23" relatw="1" move="1" visible="0"/>


	<NStatesButton id="shade.aot" x="-91" y="3" relatx="1" image="s.aot.1." hoverimage="s.aot.2." downimage="s.aot.3." rectrgn="1" cfgattrib="{280876CF-48C0-40BC-8E86-73CE6BB462E5};Always on top" nstates="2" tooltip="Toggle Always on top" cfgvals="0;1"/>
	<layer id="shade.aot.docked" x="-91" y="3" relatx="1" image="s.aot.1.1" visible="0" ghost="1"/>

	<button x="-64" relatx="1" y="3" id="player.button.minimize" action="MINIMIZE" image="s.min.1" hoverImage="s.min.2" downImage="s.min.3" rectrgn="1" tooltip="Minimize Winamp"/>
	<button id="player.button.switch" x="-44" relatx="1" y="3" action="SWITCH" param="normal" image="s.mode.1" hoverImage="s.mode.2" downImage="s.mode.3" rectrgn="1" tooltip="Main Mode"/>
	<button id="player.button.close" x="-24" relatx="1" y="3" action="CLOSE" image="s.close.1" hoverImage="s.close.2" downImage="s.close.3" rectrgn="1" tooltip="Exit Winamp"/>

	<script file="@WINAMPPATH@\Plugins\classicPro\engine\one\scripts\shade.maki" param="@SKINPATH@"/>

	<group id="cpro.shade.overlay" fitparent="1" sysregion="1"/>
	-->
</layout>